pyconnman/__init__.py
pyconnman/agent.py
pyconnman/exceptions.py
pyconnman/interface.py
pyconnman/manager.py
pyconnman/service.py
pyconnman/technology.py
pyconnman-0.2.0.dist-info/LICENSE
pyconnman-0.2.0.dist-info/METADATA
pyconnman-0.2.0.dist-info/WHEEL
pyconnman-0.2.0.dist-info/top_level.txt
pyconnman-0.2.0.dist-info/RECORD
